MANIFEST.in
README.md
setup.py
./birp/argparser.birp
./birp/codegen_utils.birp
./birp/reverse/__main__.birp
./birp/reverse/birp-rev.lark
./birp/translate/__main__.birp
./birp/translate/birp.lark
./examples/fib.birp
./examples/fizzbuzz.birp
birp/__init__.py
birp/__main__.py
birp/__version__.py
birp/argparser.py
birp/codegen_utils.py
birp/translated.py
birp.egg-info/PKG-INFO
birp.egg-info/SOURCES.txt
birp.egg-info/dependency_links.txt
birp.egg-info/not-zip-safe
birp.egg-info/requires.txt
birp.egg-info/top_level.txt
birp/reverse/__main__.py
birp/translate/__main__.py