Metadata-Version: 2.1
Name: birp
Version: 0.2.0
Summary: birp — большой русский питон (BIg Russian Python)
Home-page: https://github.com/evtn/birp
Author: evtn
Author-email: g@evtn.ru
License: MIT
Download-URL: https://github.com/evtn/birp/archive/v0.2.0.tar.gz
Keywords: python russian translation
Platform: UNKNOWN
Classifier: Intended Audience :: Developers
Classifier: Programming Language :: Python :: 3
Classifier: Programming Language :: Python :: 3.6
Classifier: Programming Language :: Python :: 3.7
Classifier: Programming Language :: Python :: 3.8
Classifier: Programming Language :: Python :: 3.9
Requires-Python: >=3.6.*
